dndice/__init__.py
dndice/core.py
dndice/lib/__init__.py
dndice/lib/evaltree.py
dndice/lib/exceptions.py
dndice/lib/helpers.py
dndice/lib/operators.py
dndice/lib/tokenizer.py
dndice/roller.py
dndice-2.8.1.dist-info/LICENSE
dndice-2.8.1.dist-info/METADATA
dndice-2.8.1.dist-info/WHEEL
dndice-2.8.1.dist-info/entry_points.txt
dndice-2.8.1.dist-info/RECORD
