Metadata-Version: 2.1
Name: dndice
Version: 2.8.1
Summary: An engine to parse and evaluate D&D-inspired roll expressions
License: GPL-2.0-or-later
Author: Nick Thurmes
Author-email: nthurmes@gmail.com
Requires-Python: >=3.5,<4.0
Classifier: License :: OSI Approved :: GNU General Public License v2 or later (GPLv2+)
Classifier: Programming Language :: Python :: 3
Classifier: Programming Language :: Python :: 3.5
Classifier: Programming Language :: Python :: 3.6
Classifier: Programming Language :: Python :: 3.7
Classifier: Programming Language :: Python :: 3.8
Classifier: Programming Language :: Python :: 3.9
Classifier: Programming Language :: Python :: 3.10
Classifier: Programming Language :: Python :: 3.11
